Workbook

Sheet Sales report
B6: Monthly Sales Report
B7: Date | C7: Day | D7: Product | E7: Quantity | F7: Sales channel | G7: Cost Price | H7: Sell Price | I7: Profit | J7: Margin | K7: Net income | L7: Revenue
B8: 43009 | C8: =TEXT(B8,"dddd") -> Sunday | D8: A | E8: 25 | F8: Amazon | G8: 10 | H8: 15 | I8: =(H8-G8) -> 5 | J8: =I8/E8 -> 0.2 | K8: =I8*E8 -> 125 | L8: =H8*E8 -> 375
B9: 43009 | C9: =TEXT(B9,"dddd") -> Sunday | D9: A | E9: 10 | F9: Website | G9: 10 | H9: 15 | I9: =(H9-G9) -> 5 | J9: =I9/E9 -> 0.5 | K9: =I9*E9 -> 50 | L9: =H9*E9 -> 150
B10: 43009 | C10: =TEXT(B10,"dddd") -> Sunday | D10: E | E10: 50 | F10: Amazon | G10: 8 | H10: 10 | I10: =(H10-G10) -> 2 | J10: =I10/E10 -> 0.04 | K10: =I10*E10 -> 100 | L10: =H10*E10 -> 500
B11: 43010 | C11: =TEXT(B11,"dddd") -> Monday | D11: B | E11: 25 | F11: Big basket | G11: 5 | H11: 10 | I11: =(H11-G11) -> 5 | J11: =I11/E11 -> 0.2 | K11: =I11*E11 -> 125 | L11: =H11*E11 -> 250
B12: 43010 | C12: =TEXT(B12,"dddd") -> Monday | D12: C | E12: 25 | F12: Website | G12: 12 | H12: 20 | I12: =(H12-G12) -> 8 | J12: =I12/E12 -> 0.32 | K12: =I12*E12 -> 200 | L12: =H12*E12 -> 500
B13: 43012 | C13: =TEXT(B13,"dddd") -> Wednesday | D13: E | E13: 10 | F13: Amazon | G13: 8 | H13: 10 | I13: =(H13-G13) -> 2 | J13: =I13/E13 -> 0.2 | K13: =I13*E13 -> 20 | L13: =H13*E13 -> 100
B14: 43012 | C14: =TEXT(B14,"dddd") -> Wednesday | D14: D | E14: 20 | F14: Flipkart | G14: 20 | H14: 30 | I14: =(H14-G14) -> 10 | J14: =I14/E14 -> 0.5 | K14: =I14*E14 -> 200 | L14: =H14*E14 -> 600
B15: 43013 | C15: =TEXT(B15,"dddd") -> Thursday | D15: C | E15: 40 | F15: Amazon | G15: 12 | H15: 20 | I15: =(H15-G15) -> 8 | J15: =I15/E15 -> 0.2 | K15: =I15*E15 -> 320 | L15: =H15*E15 -> 800
B16: 43013 | C16: =TEXT(B16,"dddd") -> Thursday | D16: D | E16: 50 | F16: Flipkart | G16: 20 | H16: 30 | I16: =(H16-G16) -> 10 | J16: =I16/E16 -> 0.2 | K16: =I16*E16 -> 500 | L16: =H16*E16 -> 1500
B17: 43014 | C17: =TEXT(B17,"dddd") -> Friday | D17: E | E17: 100 | F17: Flipkart | G17: 8 | H17: 10 | I17: =(H17-G17) -> 2 | J17: =I17/E17 -> 0.02 | K17: =I17*E17 -> 200 | L17: =H17*E17 -> 1000
B18: 43015 | C18: =TEXT(B18,"dddd") -> Saturday | D18: D | E18: 25 | F18: Big basket | G18: 20 | H18: 30 | I18: =(H18-G18) -> 10 | J18: =I18/E18 -> 0.4 | K18: =I18*E18 -> 250 | L18: =H18*E18 -> 750
B19: 43016 | C19: =TEXT(B19,"dddd") -> Sunday | D19: A | E19: 40 | F19: Big basket | G19: 10 | H19: 15 | I19: =(H19-G19) -> 5 | J19: =I19/E19 -> 0.125 | K19: =I19*E19 -> 200 | L19: =H19*E19 -> 600
... B35: 43038 | C35: =TEXT(B35,"dddd") -> Monday | D35: D | E35: 20 | F35: Amazon | G35: 20 | H35: 30 | I35: =(H35-G35) -> 10 | J35: =I35/E35 -> 0.5 | K35: =I35*E35 -> 200 | L35: =H35*E35 -> 600

Sheet Online Sales Tracker
B3: Online Sales Tracker | K3: TIPS:--
B4: Sales Summary
B5: Volume Breakup
B6: Product | C6: Website | D6: Amazon | E6: Big basket | F6: Flipkart | G6: Shopclues | H6: Volume
B7: A | C7: =SUMIFS('Sales report'!$E$8:E$35,'Sales report'!$D$8:$D$35,B7,'Sales report'!$F$8:$F$35,C6) -> 10 | D7: =SUMIFS('Sales report'!$E$8:$E$35,'Sales report'!$D$8:$D$35,B7,'Sales report'!$F$8:$F$35,D6) -> 25 | E7: =SUMIFS('Sales report'!$E$8:$E$35,'Sales report'!$D$8:$D$35,B7,'Sales report'!$F$8:$F$35,E6) -> 40 | F7: =SUMIFS('Sales report'!$E$8:$E$35,'Sales report'!$D$8:$D$35,B7,'Sales report'!$F$8:$F$35,F6) -> 0 | G7: =SUMIFS('Sales report'!$E$8:$E$35,'Sales report'!$D$8:$D$35,B7,'Sales report'!$F$8:$F$35,G6) -> 50 | H7: =SUM(C7:G7) -> 125
B8: B | C8: =SUMIFS('Sales report'!$E$8:$E$35,'Sales report'!$D$8:$D$35,B8,'Sales report'!$F$8:$F$35,C6) -> 20 | D8: =SUMIFS('Sales report'!$E$8:$E$35,'Sales report'!$D$8:$D$35,B8,'Sales report'!$F$8:$F$35,D6) -> 60 | E8: =SUMIFS('Sales report'!$E$8:$E$35,'Sales report'!$D$8:$D$35,B8,'Sales report'!$F$8:$F$35,E6) -> 115 | F8: =SUMIFS('Sales report'!$E$8:$E$35,'Sales report'!$D$8:$D$35,B8,'Sales report'!$F$8:$F$35,F6) -> 50 | G8: =SUMIFS('Sales report'!$E$8:$E$35,'Sales report'!$D$8:$D$35,B8,'Sales report'!$F$8:$F$35,G6) -> 50 | H8: =SUM(C8:G8) -> 295
B9: C | C9: =SUMIFS('Sales report'!$E$8:$E$35,'Sales report'!$D$8:$D$35,B9,'Sales report'!$F$8:$F$35,C6) -> 80 | D9: =SUMIFS('Sales report'!$E$8:$E$35,'Sales report'!$D$8:$D$35,B9,'Sales report'!$F$8:$F$35,D6) -> 40 | E9: =SUMIFS('Sales report'!$E$8:$E$35,'Sales report'!$D$8:$D$35,B9,'Sales report'!$F$8:$F$35,E6) -> 0 | F9: =SUMIFS('Sales report'!$E$8:$E$35,'Sales report'!$D$8:$D$35,B9,'Sales report'!$F$8:$F$35,F6) -> 40 | G9: =SUMIFS('Sales report'!$E$8:$E$35,'Sales report'!$D$8:$D$35,B9,'Sales report'!$F$8:$F$35,G6) -> 100 | H9: =SUM(C9:G9) -> 260
B10: D | C10: =SUMIFS('Sales report'!$E$8:$E$35,'Sales report'!$D$8:$D$35,B10,'Sales report'!$F$8:$F$35,C6) -> 45 | D10: =SUMIFS('Sales report'!$E$8:$E$35,'Sales report'!$D$8:$D$35,B10,'Sales report'!$F$8:$F$35,D6) -> 20 | E10: =SUMIFS('Sales report'!$E$8:$E$35,'Sales report'!$D$8:$D$35,B10,'Sales report'!$F$8:$F$35,E6) -> 25 | F10: =SUMIFS('Sales report'!$E$8:$E$35,'Sales report'!$D$8:$D$35,B10,'Sales report'!$F$8:$F$35,F6) -> 70 | G10: =SUMIFS('Sales report'!$E$8:$E$35,'Sales report'!$D$8:$D$35,B10,'Sales report'!$F$8:$F$35,G6) -> 25 | H10: =SUM(C10:G10) -> 185
B11: E | C11: =SUMIFS('Sales report'!$E$8:$E$35,'Sales report'!$D$8:$D$35,B11,'Sales report'!$F$8:$F$35,C6) -> 0 | D11: =SUMIFS('Sales report'!$E$8:$E$35,'Sales report'!$D$8:$D$35,B11,'Sales report'!$F$8:$F$35,D6) -> 60 | E11: =SUMIFS('Sales report'!$E$8:$E$35,'Sales report'!$D$8:$D$35,B11,'Sales report'!$F$8:$F$35,E6) -> 0 | F11: =SUMIFS('Sales report'!$E$8:$E$35,'Sales report'!$D$8:$D$35,B11,'Sales report'!$F$8:$F$35,F6) -> 200 | G11: =SUMIFS('Sales report'!$E$8:$E$35,'Sales report'!$D$8:$D$35,B11,'Sales report'!$F$8:$F$35,G6) -> 0 | H11: =SUM(C11:G11) -> 260
B12: TOTAL | C12: =SUM(C7:C11) -> 155 | D12: =SUM(D7:D11) -> 205 | E12: =SUM(E7:E11) -> 180 | F12: =SUM(F7:F11) -> 360 | G12: =SUM(G7:G11) -> 225 | H12: =SUM(C12:G12) -> 1125
B13: Product-wise Profit Breakup
B14: Product | C14: Website | D14: Amazon | E14: Big Basket | F14: Flipkart | G14: Shopclues | H14: Profit
B15: A | C15: =SUMIFS('Sales report'!$K$8:$K$35,'Sales report'!$D$8:$D$35,B15,'Sales report'!$F$8:$F$35,C14) -> 50 | D15: =SUMIFS('Sales report'!$K$8:$K$35,'Sales report'!$D$8:$D$35,B15,'Sales report'!$F$8:$F$35,D6) -> 125 | E15: =SUMIFS('Sales report'!$K$8:$K$35,'Sales report'!$D$8:$D$35,B15,'Sales report'!$F$8:$F$35,E6) -> 200 | F15: =SUMIFS('Sales report'!$K$8:$K$35,'Sales report'!$D$8:$D$35,B15,'Sales report'!$F$8:$F$35,F6) -> 0 | G15: =SUMIFS('Sales report'!$K$8:$K$35,'Sales report'!$D$8:$D$35,B15,'Sales report'!$F$8:$F$35,G6) -> 250 | H15: =SUM(C15:G15) -> 625
B16: B | C16: =SUMIFS('Sales report'!$K$8:$K$35,'Sales report'!$D$8:$D$35,B16,'Sales report'!$F$8:$F$35,C14) -> 100 | D16: =SUMIFS('Sales report'!$K$8:$K$35,'Sales report'!$D$8:$D$35,B16,'Sales report'!$F$8:$F$35,D6) -> 300 | E16: =SUMIFS('Sales report'!$K$8:$K$35,'Sales report'!$D$8:$D$35,B16,'Sales report'!$F$8:$F$35,E6) -> 575 | F16: =SUMIFS('Sales report'!$K$8:$K$35,'Sales report'!$D$8:$D$35,B16,'Sales report'!$F$8:$F$35,F6) -> 250 | G16: =SUMIFS('Sales report'!$K$8:$K$35,'Sales report'!$D$8:$D$35,B16,'Sales report'!$F$8:$F$35,G6) -> 250 | H16: =SUM(C16:G16) -> 1475
B17: C | C17: =SUMIFS('Sales report'!$K$8:$K$35,'Sales report'!$D$8:$D$35,B17,'Sales report'!$F$8:$F$35,C14) -> 640 | D17: =SUMIFS('Sales report'!$K$8:$K$35,'Sales report'!$D$8:$D$35,B17,'Sales report'!$F$8:$F$35,D6) -> 320 | E17: =SUMIFS('Sales report'!$K$8:$K$35,'Sales report'!$D$8:$D$35,B17,'Sales report'!$F$8:$F$35,E6) -> 0 | F17: =SUMIFS('Sales report'!$K$8:$K$35,'Sales report'!$D$8:$D$35,B17,'Sales report'!$F$8:$F$35,F6) -> 320 | G17: =SUMIFS('Sales report'!$K$8:$K$35,'Sales report'!$D$8:$D$35,B17,'Sales report'!$F$8:$F$35,G6) -> 800 | H17: =SUM(C17:G17) -> 2080
B18: D | C18: =SUMIFS('Sales report'!$K$8:$K$35,'Sales report'!$D$8:$D$35,B18,'Sales report'!$F$8:$F$35,C14) -> 450 | D18: =SUMIFS('Sales report'!$K$8:$K$35,'Sales report'!$D$8:$D$35,B18,'Sales report'!$F$8:$F$35,D6) -> 200 | E18: =SUMIFS('Sales report'!$K$8:$K$35,'Sales report'!$D$8:$D$35,B18,'Sales report'!$F$8:$F$35,E6) -> 250 | F18: =SUMIFS('Sales report'!$K$8:$K$35,'Sales report'!$D$8:$D$35,B18,'Sales report'!$F$8:$F$35,F6) -> 700 | G18: =SUMIFS('Sales report'!$K$8:$K$35,'Sales report'!$D$8:$D$35,B18,'Sales report'!$F$8:$F$35,G6) -> 250 | H18: =SUM(C18:G18) -> 1850
B19: E | C19: =SUMIFS('Sales report'!$K$8:$K$35,'Sales report'!$D$8:$D$35,B19,'Sales report'!$F$8:$F$35,C14) -> 0 | D19: =SUMIFS('Sales report'!$K$8:$K$35,'Sales report'!$D$8:$D$35,B19,'Sales report'!$F$8:$F$35,D6) -> 120 | E19: =SUMIFS('Sales report'!$K$8:$K$35,'Sales report'!$D$8:$D$35,B19,'Sales report'!$F$8:$F$35,E6) -> 0 | F19: =SUMIFS('Sales report'!$K$8:$K$35,'Sales report'!$D$8:$D$35,B19,'Sales report'!$F$8:$F$35,F6) -> 400 | G19: =SUMIFS('Sales report'!$K$8:$K$35,'Sales report'!$D$8:$D$35,B19,'Sales report'!$F$8:$F$35,G6) -> 0 | H19: =SUM(C19:G19) -> 520
